odoo/addons/account_invoice_report_lot_expiration_date/README.rst
odoo/addons/account_invoice_report_lot_expiration_date/__init__.py
odoo/addons/account_invoice_report_lot_expiration_date/__manifest__.py
odoo/addons/account_invoice_report_lot_expiration_date/i18n/account_invoice_report_lot_expiration_date.pot
odoo/addons/account_invoice_report_lot_expiration_date/i18n/es.po
odoo/addons/account_invoice_report_lot_expiration_date/i18n/it.po
odoo/addons/account_invoice_report_lot_expiration_date/models/__init__.py
odoo/addons/account_invoice_report_lot_expiration_date/models/account_move.py
odoo/addons/account_invoice_report_lot_expiration_date/readme/CONTRIBUTORS.rst
odoo/addons/account_invoice_report_lot_expiration_date/readme/DESCRIPTION.rst
odoo/addons/account_invoice_report_lot_expiration_date/report/report_invoice.xml
odoo/addons/account_invoice_report_lot_expiration_date/static/description/icon.png
odoo/addons/account_invoice_report_lot_expiration_date/static/description/index.html
odoo/addons/account_invoice_report_lot_expiration_date/tests/__init__.py
odoo/addons/account_invoice_report_lot_expiration_date/tests/test_invoice_production_lot.py
odoo_addon_account_invoice_report_lot_expiration_date-16.0.1.0.0.4.dist-info/METADATA
odoo_addon_account_invoice_report_lot_expiration_date-16.0.1.0.0.4.dist-info/WHEEL
odoo_addon_account_invoice_report_lot_expiration_date-16.0.1.0.0.4.dist-info/top_level.txt
odoo_addon_account_invoice_report_lot_expiration_date-16.0.1.0.0.4.dist-info/RECORD
