Metadata-Version: 2.1
Name: odoo-addon-account_invoice_report_lot_expiration_date
Version: 16.0.1.0.0.4
Summary: This addon adds the batch expiration date to the invoice.
Home-page: https://github.com/OCA/account-invoice-reporting
Author: Binhex,Odoo Community Association (OCA)
Author-email: support@odoo-community.org
License: AGPL-3
Classifier: Programming Language :: Python
Classifier: Framework :: Odoo
Classifier: Framework :: Odoo :: 16.0
Classifier: License :: OSI Approved :: GNU Affero General Public License v3
Requires-Python: >=3.10
Requires-Dist: odoo<16.1dev,>=16.0a
